plugin/__init__.py
plugin/plugin.py
mkdocs_user_defined_values-0.0.5.dist-info/METADATA
mkdocs_user_defined_values-0.0.5.dist-info/WHEEL
mkdocs_user_defined_values-0.0.5.dist-info/entry_points.txt
mkdocs_user_defined_values-0.0.5.dist-info/top_level.txt
mkdocs_user_defined_values-0.0.5.dist-info/RECORD
